phi_utils/__init__.py
phi_utils/_utils/settings.py
phi_utils/edit/__init__.py
phi_utils/edit/saves.py
phi_utils/models/__init__.py
phi_utils/models/bN.py
phi_utils/models/difficulty.py
phi_utils/models/info.py
phi_utils/models/saves.py
phi_utils-0.1.0.dist-info/licenses/LICENSE
phi_utils-0.1.0.dist-info/METADATA
phi_utils-0.1.0.dist-info/WHEEL
phi_utils-0.1.0.dist-info/top_level.txt
phi_utils-0.1.0.dist-info/RECORD
