Metadata-Version: 2.4
Name: phi_utils
Version: 0.1.0
Summary: Phigros相关工具
Author-email: Shua-github <CHA_shua@outlook.com>
License: MIT
Requires-Python: >=3.9
License-File: LICENSE
Requires-Dist: Pydantic>=2.10.6
Dynamic: license-file
